pdftopng/cli.py
pdftopng/__main__.py
pdftopng/foo.py
pdftopng/__init__.py
pdftopng/pdftopng.cpp
pdftopng/pdftopng.cpython-39-x86_64-linux-gnu.so
pdftopng/__version__.py
pdftopng.libs/libz-eb09ad1d.so.1.2.3
pdftopng.libs/libfreetype-20bfc0cd.so.6.3.22
pdftopng.libs/libexpat-64fa60ba.so.1.5.2
pdftopng.libs/libpoppler-a7a78804.so.103.0.0
pdftopng.libs/libjpeg-7feae879.so.62.0.0
pdftopng.libs/libpng12-640ca796.so.0.49.0
pdftopng.libs/libfontconfig-63352676.so.1.4.4
pdftopng-0.2.2.dist-info/LICENSE
pdftopng-0.2.2.dist-info/WHEEL
pdftopng-0.2.2.dist-info/top_level.txt
pdftopng-0.2.2.dist-info/METADATA
pdftopng-0.2.2.dist-info/entry_points.txt
pdftopng-0.2.2.dist-info/RECORD
