Metadata-Version: 2.1
Name: pdftopng
Version: 0.2.2
Summary: A PDF to PNG conversion library.
Home-page: https://github.com/vinayak-mehta/pdftopng
Author: Vinayak Mehta
Author-email: vmehta94@gmail.com
License: GPL-2.0
Platform: UNKNOWN
Classifier: License :: OSI Approved :: GNU General Public License v2 (GPLv2)
Classifier: Programming Language :: Python :: 3.6
Classifier: Programming Language :: Python :: 3.7
Classifier: Programming Language :: Python :: 3.8
License-File: LICENSE
Requires-Dist: Click (>=7.0)
Provides-Extra: dev
Requires-Dist: Pillow (>=8.2.0) ; extra == 'dev'
Requires-Dist: pytest (>=6.2.3) ; extra == 'dev'
Requires-Dist: pytest-cov (>=2.11.1) ; extra == 'dev'
Requires-Dist: Click (>=7.0) ; extra == 'dev'
